fabricatio_rag-0.1.13.dist-info/METADATA
fabricatio_rag-0.1.13.dist-info/WHEEL
fabricatio_rag-0.1.13.dist-info/licenses/LICENSE
fabricatio_rag/__init__.py
fabricatio_rag/actions/__init__.py
fabricatio_rag/actions/rag.py
fabricatio_rag/capabilities/__init__.py
fabricatio_rag/capabilities/rag.py
fabricatio_rag/config.py
fabricatio_rag/models/__init__.py
fabricatio_rag/models/kwargs_types.py
fabricatio_rag/models/rag.py
fabricatio_rag/py.typed
fabricatio_rag/rust.cpython-312-x86_64-linux-gnu.so
fabricatio_rag/rust.pyi
fabricatio_rag/workflows/__init__.py
fabricatio_rag-0.1.13.dist-info/RECORD
