Metadata-Version: 2.4
Name: fabricatio-rag
Version: 0.1.13
Requires-Dist: pymilvus>=2.5.4
Requires-Dist: pydantic>=2.7.4
Requires-Dist: fabricatio-core
License-File: LICENSE
Summary: A Python library for Retrieval-Augmented Generation (RAG) capabilities in LLM applications.
Author-email: Whth <zettainspector@foxmail.com>
Requires-Python: >=3.12, <3.15
Project-URL: Homepage, https://github.com/Whth/fabricatio
Project-URL: Repository, https://github.com/Whth/fabricatio
Project-URL: Issues, https://github.com/Whth/fabricatio/issues
